mcp_server_milvus/__init__.py
mcp_server_milvus/blogpost.md
mcp_server_milvus/server.py
milvus_mcp_server-0.1.0.dist-info/METADATA
milvus_mcp_server-0.1.0.dist-info/WHEEL
milvus_mcp_server-0.1.0.dist-info/entry_points.txt
milvus_mcp_server-0.1.0.dist-info/top_level.txt
milvus_mcp_server-0.1.0.dist-info/RECORD
