Metadata-Version: 2.4
Name: milvus-mcp-server
Version: 0.1.0
Summary: Add your description here
Requires-Python: >=3.13
Requires-Dist: asyncio>=3.4.3
Requires-Dist: click>=8.1.8
Requires-Dist: dotenv>=0.9.9
Requires-Dist: mcp[cli]>=1.4.1
Requires-Dist: pymilvus>=2.5.5
Requires-Dist: ruff>=0.11.0
